{
  "2024-03-30": {
    "present": [
      "670999",
      "670556",
      "670978",
      "640934",
      "670557",
      "670557",
      "670556",
      "89"
    ],
    "absent": [
      "670999",
      "670556",
      "670978",
      "640934",
      "670557",
      "670557",
      "670556",
      "89"
    ],
    "excused": [
      "670999",
      "670556",
      "670978",
      "640934",
      "670557",
      "670557",
      "670556",
      "89"
    ]
  },
  "2024-03-20": {
    "present": [
      "670999",
      "670556",
      "670978",
      "640934",
      "670557",
      "670557",
      "670556",
      "89"
    ],
    "absent": [
      "670999",
      "670556",
      "670978",
      "640934",
      "670557",
      "670557",
      "670556",
      "89"
    ],
    "excused": [
      "670999",
      "670556",
      "670978",
      "640934",
      "670557",
      "670557",
      "670556",
      "89"
    ]
  }
}